mapchete_hub_cli/__init__.py
mapchete_hub_cli/client.py
mapchete_hub_cli/enums.py
mapchete_hub_cli/exceptions.py
mapchete_hub_cli/job.py
mapchete_hub_cli/log.py
mapchete_hub_cli/parser.py
mapchete_hub_cli/time.py
mapchete_hub_cli/types.py
mapchete_hub_cli/cli/__init__.py
mapchete_hub_cli/cli/cancel.py
mapchete_hub_cli/cli/clean.py
mapchete_hub_cli/cli/execute.py
mapchete_hub_cli/cli/job.py
mapchete_hub_cli/cli/jobs.py
mapchete_hub_cli/cli/main.py
mapchete_hub_cli/cli/options.py
mapchete_hub_cli/cli/processes.py
mapchete_hub_cli/cli/progress.py
mapchete_hub_cli/cli/retry.py
mapchete_hub_cli/cli/show_remote_version.py
mapchete_hub_cli/cli/test.py
mapchete_hub_cli-2025.9.0.dist-info/METADATA
mapchete_hub_cli-2025.9.0.dist-info/WHEEL
mapchete_hub_cli-2025.9.0.dist-info/entry_points.txt
mapchete_hub_cli-2025.9.0.dist-info/licenses/LICENSE
mapchete_hub_cli-2025.9.0.dist-info/RECORD
