Metadata-Version: 2.4
Name: mapchete-hub-cli
Version: 2025.9.0
Summary: CLI and Python bindings to mapchete Hub API.
Project-URL: Homepage, https://github.com/mapchete/mapchete-hub-cli
Author-email: Joachim Ungar <joachim.ungar@eox.at>, Petr Sevcik <petr.sevcik@eox.at>
License-Expression: MIT
License-File: LICENSE
Classifier: Development Status :: 4 - Beta
Classifier: Intended Audience :: Developers
Classifier: License :: OSI Approved :: MIT License
Classifier: Programming Language :: Python :: 3.9
Classifier: Programming Language :: Python :: 3.10
Classifier: Programming Language :: Python :: 3.11
Classifier: Topic :: Scientific/Engineering :: GIS
Requires-Python: >=3.9
Requires-Dist: click
Requires-Dist: click-plugins
Requires-Dist: click-spinner
Requires-Dist: oyaml
Requires-Dist: pydantic
Requires-Dist: python-dateutil
Requires-Dist: requests
Requires-Dist: tqdm
Provides-Extra: test
Requires-Dist: mapchete-hub>=2023.12.0; extra == 'test'
Requires-Dist: pytest; extra == 'test'
Requires-Dist: pytest-cov; extra == 'test'
Requires-Dist: pytest-env; extra == 'test'
Requires-Dist: requests; extra == 'test'
Provides-Extra: zones
Requires-Dist: mapchete; extra == 'zones'
